scoutrss/__init__.py
scoutrss/socutrss.py
watchrss/__init__.py
watchrss/watchrss.py
scoutrss-0.1.0.dist-info/LICENSE
scoutrss-0.1.0.dist-info/METADATA
scoutrss-0.1.0.dist-info/WHEEL
scoutrss-0.1.0.dist-info/top_level.txt
scoutrss-0.1.0.dist-info/RECORD
