Metadata-Version: 2.1
Name: scoutrss
Version: 0.1.0
Summary: A library for watching RSS feeds and notifying when new entries are available
Home-page: https://github.com/viperadnan-git/scoutrss
Author: Adnan Ahmad
Author-email: viperadnan@gmail.com
License: GNU General Public License v3.0
Classifier: Development Status :: 5 - Production/Stable
Classifier: Intended Audience :: Developers
Classifier: License :: OSI Approved :: GNU General Public License v3 or later (GPLv3+)
Classifier: Programming Language :: Python :: 3
Classifier: Programming Language :: Python :: 3.6
Classifier: Programming Language :: Python :: 3.7
Classifier: Programming Language :: Python :: 3.8
Classifier: Programming Language :: Python :: 3.9
License-File: LICENSE
Requires-Dist: pickledb
Requires-Dist: apscheduler
Requires-Dist: feedparser
